main.py
server.py
iflow_mcp_stevenyu113228_bloodhound_mcp-0.1.2.dist-info/METADATA
iflow_mcp_stevenyu113228_bloodhound_mcp-0.1.2.dist-info/WHEEL
iflow_mcp_stevenyu113228_bloodhound_mcp-0.1.2.dist-info/entry_points.txt
iflow_mcp_stevenyu113228_bloodhound_mcp-0.1.2.dist-info/top_level.txt
iflow_mcp_stevenyu113228_bloodhound_mcp-0.1.2.dist-info/RECORD
