Metadata-Version: 2.4
Name: iflow-mcp_stevenyu113228_bloodhound_mcp
Version: 0.1.2
Summary: Add your description here
Requires-Python: >=3.11
Requires-Dist: mcp[cli]>=1.6.0
Requires-Dist: neo4j>=5.28.1
